copy_orchid_examples.py
copy_orchid_low_level_examples.py
copy_orchid_manual_examples.py
copy_orchid_tutorials.py
LICENSE
orchid/__init__.py
orchid/__version__.py
orchid/base.py
orchid/base_time_series_adapter.py
orchid/configuration.py
orchid/convert.py
orchid/core.py
orchid/dom_project_object.py
orchid/dot_net.py
orchid/dot_net_disposable.py
orchid/dot_net_dom_access.py
orchid/measurement.py
orchid/native_data_frame_adapter.py
orchid/native_monitor_adapter.py
orchid/native_project_user_data_adapter.py
orchid/native_stage_adapter.py
orchid/native_stage_part_adapter.py
orchid/native_subsurface_point.py
orchid/native_time_series_adapter.py
orchid/native_trajectory_adapter.py
orchid/native_treatment_calculations.py
orchid/native_treatment_curve_adapter.py
orchid/native_well_adapter.py
orchid/net_date_time.py
orchid/net_enumerable.py
orchid/net_fracture_diagnostics_factory.py
orchid/net_quantity.py
orchid/net_stage_qc.py
orchid/physical_quantity.py
orchid/project.py
orchid/project_store.py
orchid/reference_origins.py
orchid/script_adapter_context.py
orchid/searchable_data_frames.py
orchid/searchable_project_objects.py
orchid/searchable_stage_parts.py
orchid/searchable_stages.py
orchid/unit_system.py
orchid/validation.py
orchid/VERSION
orchid/version.py
orchid_python_api/__init__.py
orchid_python_api/examples/add_stages.py
orchid_python_api/examples/change_stage_times.py
orchid_python_api/examples/completion_analysis.ipynb
orchid_python_api/examples/completion_analysis.py
orchid_python_api/examples/low_level/add_stages_low.py
orchid_python_api/examples/low_level/auto_pick.ipynb
orchid_python_api/examples/low_level/auto_pick.py
orchid_python_api/examples/low_level/auto_pick_and_create_stage_attribute.py
orchid_python_api/examples/low_level/auto_pick_iterate_example.py
orchid_python_api/examples/low_level/monitor_time_series.py
orchid_python_api/examples/low_level/multi_picking_events.py
orchid_python_api/examples/manual/data_frame_with_guid.ipynb
orchid_python_api-2023.1.220.dist-info/entry_points.txt
orchid_python_api-2023.1.220.dist-info/LICENSE
orchid_python_api-2023.1.220.dist-info/METADATA
orchid_python_api-2023.1.220.dist-info/WHEEL
orchid_python_api-2023.1.220.dist-info/RECORD
