Metadata-Version: 2.1
Name: orchid-python-api
Version: 2023.1.220
Summary: Defines and implements the Python API for Orchid*. (*Orchid is a mark of Reveal Energy Services, Inc.)
Home-page: https://github.com/Reveal-Energy-Services/orchid-python-api
License: Apache-2.0
Keywords: Orchid Integration,Fracture Diagnostics
Author: Reveal Energy Services, Inc.
Author-email: support@reveal-energy.com
Maintainer: Reveal Energy Services, Inc.
Maintainer-email: support@reveal-energy.com
Requires-Python: >=3.10,<3.11
Classifier: Development Status :: 5 - Production/Stable
Classifier: Intended Audience :: Other Audience
Classifier: Intended Audience :: Science/Research
Classifier: License :: OSI Approved :: Apache Software License
Classifier: Operating System :: Microsoft :: Windows :: Windows 10
Classifier: Programming Language :: Python
Classifier: Programming Language :: Python :: 3
Classifier: Programming Language :: Python :: 3.10
Classifier: Programming Language :: Python :: 3
Classifier: Programming Language :: Python :: 3.10
Classifier: Programming Language :: Python :: Implementation :: CPython
Classifier: Topic :: Scientific/Engineering
Classifier: Topic :: Software Development :: Libraries
Classifier: Topic :: Software Development :: Libraries :: Python Modules
Requires-Dist: deal (>=4.23.4,<5.0.0)
Requires-Dist: ipython (>=8.7.0,<9.0.0)
Requires-Dist: jupyter (>=1.0.0,<2.0.0)
Requires-Dist: jupyterlab (>=3.5.1,<4.0.0)
Requires-Dist: matplotlib (>=3.6.2,<4.0.0)
Requires-Dist: numpy (>=1.23.5,<2.0.0)
Requires-Dist: option (>=2.1.0,<3.0.0)
Requires-Dist: packaging (>=22.0,<23.0)
Requires-Dist: pandas (>=1.5.2,<2.0.0)
Requires-Dist: pendulum (>=2.1.2,<3.0.0)
Requires-Dist: pint (>=0.20.1,<0.21.0)
Requires-Dist: python-dateutil (>=2.8.2,<3.0.0)
Requires-Dist: pythonnet (==3.0.0-post1)
Requires-Dist: pyyaml (>=6.0,<7.0)
Requires-Dist: scipy (>=1.9.3,<2.0.0)
Requires-Dist: seaborn (>=0.12.1,<0.13.0)
Requires-Dist: toolz (>=0.12.0,<0.13.0)
Requires-Dist: typing-extensions (>=4.4.0,<5.0.0)
Project-URL: Documentation, https://github.com/Reveal-Energy-Services/orchid-python-api/wiki
Project-URL: Issues, https://github.com/Reveal-Energy-Services/orchid-python-api/issues
Project-URL: Repository, https://github.com/Reveal-Energy-Services/orchid-python-api
